wapsok/__init__.py
wapsok/main.py
wapsok-0.2.dist-info/METADATA
wapsok-0.2.dist-info/WHEEL
wapsok-0.2.dist-info/top_level.txt
wapsok-0.2.dist-info/RECORD
