Metadata-Version: 2.1
Name: wapsok
Version: 0.2
Summary: something
Home-page: https://github.com/ex0f
Author: exy
Author-email: ex@exy.lol
Classifier: Programming Language :: Python :: 3
Classifier: License :: OSI Approved :: MIT License
Classifier: Operating System :: OS Independent
Requires-Python: >=3.6
Requires-Dist: requests
